fixed_asset_plugin/__init__.py
fixed_asset_plugin/core.py
fixed_asset_plugin-0.1.0.dist-info/licenses/LICENSE
fixed_asset_plugin-0.1.0.dist-info/METADATA
fixed_asset_plugin-0.1.0.dist-info/WHEEL
fixed_asset_plugin-0.1.0.dist-info/entry_points.txt
fixed_asset_plugin-0.1.0.dist-info/top_level.txt
fixed_asset_plugin-0.1.0.dist-info/RECORD
